pyssq/__init__.py
pyssq/doublecolor.py
pyssq/utils.py
pyssq-0.1.1.dist-info/METADATA
pyssq-0.1.1.dist-info/WHEEL
pyssq-0.1.1.dist-info/top_level.txt
pyssq-0.1.1.dist-info/RECORD
