Metadata-Version: 2.4
Name: pyssq
Version: 0.1.1
Summary: Add your description here
Requires-Python: >=3.12
